showast/__init__.py
showast/asts.py
showast/rendering/__init__.py
showast/rendering/graphviz.py
showast/rendering/nltk.py
showast/util/__init__.py
showast/util/contextmanagers.py
showast-0.2.4.dist-info/DESCRIPTION.rst
showast-0.2.4.dist-info/METADATA
showast-0.2.4.dist-info/RECORD
showast-0.2.4.dist-info/WHEEL
showast-0.2.4.dist-info/metadata.json
showast-0.2.4.dist-info/top_level.txt
