Metadata-Version: 2.0
Name: showast
Version: 0.2.4
Summary: IPython notebook plugin for visualizing abstract syntax trees.
Home-page: https://github.com/hchasestevens/show_ast
Author: H. Chase Stevens
Author-email: chase@chasestevens.com
License: MIT
Keywords: ipython jupyter notebook ast asts graphing visualization syntax
Platform: UNKNOWN
Classifier: Development Status :: 3 - Alpha
Classifier: Programming Language :: Python
Classifier: Programming Language :: Python :: 2
Classifier: Programming Language :: Python :: 2.7
Classifier: Intended Audience :: Developers
Classifier: Operating System :: OS Independent
Classifier: License :: OSI Approved :: MIT License
Classifier: Natural Language :: English
Classifier: Topic :: Software Development :: Code Generators
Classifier: Framework :: IPython
Classifier: Topic :: Multimedia :: Graphics :: Presentation
Requires-Dist: graphviz
Requires-Dist: ipython
Provides-Extra: nltk
Requires-Dist: nltk; extra == 'nltk'
Requires-Dist: pillow; extra == 'nltk'
